google/cloud/appengine_admin/__init__.py
google/cloud/appengine_admin/gapic_version.py
google/cloud/appengine_admin/py.typed
google/cloud/appengine_admin_v1/__init__.py
google/cloud/appengine_admin_v1/gapic_metadata.json
google/cloud/appengine_admin_v1/gapic_version.py
google/cloud/appengine_admin_v1/py.typed
google/cloud/appengine_admin_v1/services/__init__.py
google/cloud/appengine_admin_v1/services/applications/__init__.py
google/cloud/appengine_admin_v1/services/applications/async_client.py
google/cloud/appengine_admin_v1/services/applications/client.py
google/cloud/appengine_admin_v1/services/applications/transports/__init__.py
google/cloud/appengine_admin_v1/services/applications/transports/base.py
google/cloud/appengine_admin_v1/services/applications/transports/grpc.py
google/cloud/appengine_admin_v1/services/applications/transports/grpc_asyncio.py
google/cloud/appengine_admin_v1/services/applications/transports/rest.py
google/cloud/appengine_admin_v1/services/applications/transports/rest_base.py
google/cloud/appengine_admin_v1/services/authorized_certificates/__init__.py
google/cloud/appengine_admin_v1/services/authorized_certificates/async_client.py
google/cloud/appengine_admin_v1/services/authorized_certificates/client.py
google/cloud/appengine_admin_v1/services/authorized_certificates/pagers.py
google/cloud/appengine_admin_v1/services/authorized_certificates/transports/__init__.py
google/cloud/appengine_admin_v1/services/authorized_certificates/transports/base.py
google/cloud/appengine_admin_v1/services/authorized_certificates/transports/grpc.py
google/cloud/appengine_admin_v1/services/authorized_certificates/transports/grpc_asyncio.py
google/cloud/appengine_admin_v1/services/authorized_certificates/transports/rest.py
google/cloud/appengine_admin_v1/services/authorized_certificates/transports/rest_base.py
google/cloud/appengine_admin_v1/services/authorized_domains/__init__.py
google/cloud/appengine_admin_v1/services/authorized_domains/async_client.py
google_cloud_appengine_admin-1.16.0.dist-info/licenses/LICENSE
google_cloud_appengine_admin-1.16.0.dist-info/METADATA
google_cloud_appengine_admin-1.16.0.dist-info/WHEEL
google_cloud_appengine_admin-1.16.0.dist-info/top_level.txt
google_cloud_appengine_admin-1.16.0.dist-info/RECORD
